{
    "phpmyadmin": {
        "produit": [
            {
                "114": {
                    "titre": {
                        "fr": "ujvujgub",
                        "en": "huh"
                    },
                    "description": {
                        "fr": "uh",
                        "en": "huhuhhuju"
                    },
                    "raisons": {
                        "fr": "huhuhuh",
                        "en": "huhu"
                    }
                }
            }
        ],
        "game": [
            {
                "9": {
                    "titre": {
                        "fr": "chasse au tr\u00e9sor",
                        "en": "chasse in tresor"
                    },
                    "groupe_cible": {
                        "fr": "enfant",
                        "en": "kids"
                    }
                }
            },
            {
                "10": {
                    "titre": {
                        "fr": "chasse au tr\u00e9sor",
                        "en": "chasse in tresor"
                    },
                    "groupe_cible": {
                        "fr": "enfant",
                        "en": "kids"
                    }
                }
            },
            {
                "11": {
                    "titre": {
                        "fr": "chasse magique",
                        "en": "chasse in tresor"
                    },
                    "groupe_cible": {
                        "fr": "enfant",
                        "en": "kids"
                    }
                }
            },
            {
                "12": {
                    "titre": {
                        "fr": "rgr",
                        "en": "vjv f"
                    },
                    "groupe_cible": {
                        "fr": "jijj",
                        "en": "fjr "
                    }
                }
            },
            {
                "13": {
                    "titre": {
                        "fr": "rgr",
                        "en": "vjv f"
                    },
                    "groupe_cible": {
                        "fr": "jijj",
                        "en": "fjr "
                    }
                }
            }
        ],
        "version": [
            {
                "6": {
                    "histoire": {
                        "fr": "rjfiirfjru",
                        "en": "jiji"
                    },
                    "description": {
                        "fr": "jipi,juh uh uhu ",
                        "en": "hu hup "
                    },
                    "adresse": {
                        "fr": "jij",
                        "en": "jij"
                    },
                    "rdv": {
                        "fr": "h h",
                        "en": "huh"
                    },
                    "info_importante": {
                        "fr": "ygy",
                        "en": "huhu"
                    },
                    "exigence": {
                        "fr": "huh",
                        "en": "huh"
                    },
                    "contenu": {
                        "fr": "j uh__uh",
                        "en": "huhuj"
                    },
                    "a_apporter": {
                        "fr": "juh huh",
                        "en": "huh"
                    },
                    "autre": {
                        "fr": "huhuh",
                        "en": "huh"
                    }
                }
            },
            {
                "7": {
                    "histoire": {
                        "fr": "l'histoire",
                        "en": "the historie"
                    },
                    "description": {
                        "fr": "la description",
                        "en": "the description"
                    },
                    "adresse": {
                        "fr": "rue truc",
                        "en": "road truc"
                    },
                    "rdv": {
                        "fr": "fr",
                        "en": "en"
                    },
                    "info_importante": {
                        "fr": "ygy",
                        "en": "huhu"
                    },
                    "exigence": {
                        "fr": "huh",
                        "en": "huh"
                    },
                    "contenu": {
                        "fr": "fr",
                        "en": "en"
                    },
                    "a_apporter": {
                        "fr": "juh huh",
                        "en": "huh"
                    },
                    "autre": {
                        "fr": "fr",
                        "en": "en"
                    }
                }
            },
            {
                "8": {
                    "histoire": {
                        "fr": "l'histoire",
                        "en": "the historie"
                    },
                    "description": {
                        "fr": "la description",
                        "en": "the description"
                    },
                    "adresse": {
                        "fr": "rue truc",
                        "en": "road truc"
                    },
                    "rdv": {
                        "fr": "fr",
                        "en": "en"
                    },
                    "info_importante": {
                        "fr": "ygy",
                        "en": "huhu"
                    },
                    "exigence": {
                        "fr": "huh",
                        "en": "huh"
                    },
                    "contenu": {
                        "fr": "fr",
                        "en": "en"
                    },
                    "a_apporter": {
                        "fr": "juh huh",
                        "en": "huh"
                    },
                    "autre": {
                        "fr": "fr",
                        "en": "en"
                    }
                }
            },
            {
                "9": {
                    "histoire": {
                        "fr": "l'histoire",
                        "en": "the historie"
                    },
                    "description": {
                        "fr": "la description",
                        "en": "the description"
                    },
                    "adresse": {
                        "fr": "rue truc",
                        "en": "road truc"
                    },
                    "rdv": {
                        "fr": "fr",
                        "en": "en"
                    },
                    "info_importante": {
                        "fr": "ygy",
                        "en": "huhu"
                    },
                    "exigence": {
                        "fr": "huh",
                        "en": "huh"
                    },
                    "contenu": {
                        "fr": "fr",
                        "en": "en"
                    },
                    "a_apporter": {
                        "fr": "juh huh",
                        "en": "huh"
                    },
                    "autre": {
                        "fr": "fr",
                        "en": "en"
                    }
                }
            },
            {
                "10": {
                    "histoire": {
                        "fr": "l'histoire",
                        "en": "the historie"
                    },
                    "description": {
                        "fr": "la description",
                        "en": "the description"
                    },
                    "adresse": {
                        "fr": "rue truc",
                        "en": "road truc"
                    },
                    "rdv": {
                        "fr": "fr",
                        "en": "en"
                    },
                    "info_importante": {
                        "fr": "ygy",
                        "en": "huhu"
                    },
                    "exigence": {
                        "fr": "huh",
                        "en": "huh"
                    },
                    "contenu": {
                        "fr": "fr",
                        "en": "en"
                    },
                    "a_apporter": {
                        "fr": "juh huh",
                        "en": "huh"
                    },
                    "autre": {
                        "fr": "fr",
                        "en": "en"
                    }
                }
            },
            {
                "11": {
                    "histoire": {
                        "fr": "l'histoire",
                        "en": "the historie"
                    },
                    "description": {
                        "fr": "la description",
                        "en": "the description"
                    },
                    "adresse": {
                        "fr": "rue truc",
                        "en": "road truc"
                    },
                    "rdv": {
                        "fr": "fr merveil",
                        "en": "en merveil"
                    },
                    "info_importante": {
                        "fr": "ygy",
                        "en": "huhu"
                    },
                    "exigence": {
                        "fr": "huh",
                        "en": "huh"
                    },
                    "contenu": {
                        "fr": "fr",
                        "en": "en"
                    },
                    "a_apporter": {
                        "fr": "juh huh",
                        "en": "huh"
                    },
                    "autre": {
                        "fr": "fr Merlin",
                        "en": "en Merlin"
                    }
                }
            },
            {
                "12": {
                    "histoire": {
                        "fr": "v v",
                        "en": " jivj "
                    },
                    "description": {
                        "fr": "frfr",
                        "en": "bjfbf j"
                    },
                    "adresse": {
                        "fr": "y \u00e8y",
                        "en": "y\u00e8yn"
                    },
                    "rdv": {
                        "fr": "vfvjvff",
                        "en": "jih"
                    },
                    "info_importante": {
                        "fr": "hui",
                        "en": ""
                    },
                    "exigence": {
                        "fr": "hu",
                        "en": ""
                    },
                    "contenu": {
                        "fr": "huho",
                        "en": "hui"
                    },
                    "a_apporter": {
                        "fr": "huio",
                        "en": "hui"
                    },
                    "autre": {
                        "fr": "",
                        "en": ""
                    }
                }
            },
            {
                "13": {
                    "histoire": {
                        "fr": "v v",
                        "en": " jivj "
                    },
                    "description": {
                        "fr": "frfr",
                        "en": "bjfbf j"
                    },
                    "adresse": {
                        "fr": "y \u00e8y",
                        "en": "y\u00e8yn"
                    },
                    "rdv": {
                        "fr": "vfvjvff",
                        "en": "jih"
                    },
                    "info_importante": {
                        "fr": "hui",
                        "en": ""
                    },
                    "exigence": {
                        "fr": "hu",
                        "en": ""
                    },
                    "contenu": {
                        "fr": "huho",
                        "en": "hui"
                    },
                    "a_apporter": {
                        "fr": "huio",
                        "en": "hui"
                    },
                    "autre": {
                        "fr": "",
                        "en": ""
                    }
                }
            }
        ]
    },
    "header": {
        "menu1": {
            "fr": "Nos aventures",
            "en": "Our adventures"
        },
        "menu2": {
            "fr": "R\u00e9servations",
            "en": "Reservations"
        },
        "menu3": {
            "fr": "Cartes cadeaux",
            "en": "Gift cards"
        },
        "menu4": {
            "fr": "Contact",
            "en": "Contact"
        }
    },
    "footer": {
        "description": {
            "fr": "",
            "en": ""
        },
        "action": {
            "fr": "Pr\u00eat ? Partez !",
            "en": "Ready ? Go !"
        },
        "info": {
            "titre": {
                "fr": "Informations",
                "en": "Informations"
            },
            "1": {
                "fr": "Mentions l\u00e9gales",
                "en": "Legal information"
            },
            "2": {
                "fr": "Conditions g\u00e9n\u00e9rales de ventes",
                "en": "Terms and conditions of sale"
            },
            "3": {
                "fr": "Politique de confidentialit\u00e9",
                "en": "Privacy policy"
            }
        }
    },
    "accueil": {
        "slogan": {
            "fr": "Escape game en plein air : <br>Alsace, myst\u00e8re \u00e0 ciel ouvert !",
            "en": "Open-air Escape game : <br>Alsace, an open-air mystery!"
        },
        "description": {
            "fr": "Explorez l'Alsace en \u00e9nigmes avec notre escape game en plein air : des \u00e9nigmes, des d\u00e9fis et une aventure captivante \u00e0 vivre en \u00e9quipe !",
            "en": "Explore Alsace in enigmas with our outdoor escape game: enigmas, challenges and a captivating adventure to enjoy as a team!"
        },
        "bouton": {
            "fr": "3,2,1 r\u00e9servez !",
            "en": "3,2,1, book now !"
        }
    },
    "contact": {
        "titre": {
            "fr": "Contactez-nous !",
            "en": "Get in touch!"
        },
        "description": {
            "fr": "Votre satisfaction est notre priorit\u00e9e ! N'h\u00e9sitez pas \u00e0 nous contacter si vous avez une question. Nous vous r\u00e9pondrons dans un d\u00e9lai maximal de 48h.",
            "en": "Your satisfaction is our priority! Please do not hesitate to contact us if you have any questions. We'll get back to you within 48 hours."
        },
        "nom-prenom": {
            "fr": "NOM Pr\u00e9nom *",
            "en": "NAME First name"
        },
        "email": {
            "fr": "Adresse mail *",
            "en": "Email address *"
        },
        "tel": {
            "fr": "Num\u00e9ro de t\u00e9l\u00e9phone *",
            "en": "Telephone number *"
        },
        "objet": {
            "label": {
                "fr": "Objet *",
                "en": "Object *"
            },
            "1": {
                "fr": "Demande d'information",
                "en": "Information request"
            },
            "2": {
                "fr": "Probl\u00e8me de r\u00e9servation",
                "en": "Booking problems"
            },
            "3": {
                "fr": "R\u00e9clamation",
                "en": "Claims"
            },
            "4": {
                "fr": "Candidature",
                "en": "Application"
            },
            "5": {
                "fr": "Autre",
                "en": "Other"
            }
        },
        "message": {
            "fr": "Votre message ... ",
            "en": "Your message ... "
        },
        "envoie": {
            "fr": "Envoyer",
            "en": "Send"
        }
    },
    "adminAjout": {
        "titre": {
            "fr": "Titre *",
            "en": ""
        },
        "cible": {
            "fr": "Groupes cible *",
            "en": ""
        },
        "description": {
            "fr": "Description *",
            "en": ""
        },
        "photoPrincipale": {
            "fr": "Ajouter la photo principale *",
            "en": ""
        },
        "prix": {
            "fr": "Prix *",
            "en": ""
        },
        "duree": {
            "fr": "Durée *",
            "en": ""
        },"heures": {
            "fr": "heures",
            "en": ""
        },
        "langues": {
            "label": {
                "fr": "Langues *",
                "en": ""
            },
            "1": {
                "fr": "Français",
                "en": ""
            },
            "2": {
                "fr": "Anglais",
                "en": ""
            }
        },
        "histoire": {
            "fr": "Histoire *",
            "en": ""
        },
        "adresse": {
            "fr": "Adresse *",
            "en": ""
        },
        "ville": {
            "fr": "Ville *",
            "en": ""
        },
        "code_postal": {
            "fr": "Code Postal *",
            "en": ""
        },
        "coordonne": {
            "fr": "Coordonné (X.XXX,Y.YYYY)",
            "en": ""
        },
        "transports": {
            "label": {
                "fr": "Transports *",
                "en": ""
            },
            "1": {
                "fr": "Parking",
                "en": ""
            },
            "2": {
                "fr": "Train",
                "en": ""
            },
            "3": {
                "fr": "Bus",
                "en": ""
            }
        },
        "photos": {
            "fr": "Ajouter plus de photos",
            "en": ""
        },
        "niveau": {
            "parcours": {
                "fr": "Niveau du parcours *",
                "en": ""
            },
            "puzzle": {
                "fr": "Niveau des puzzles *",
                "en": ""
            },
            "1": {
                "fr": "Facile",
                "en": ""
            },
            "2": {
                "fr": "Moyen",
                "en": ""
            },
            "3": {
                "fr": "Difficile",
                "en": ""
            }
        },
        "nbclient": {
            "fr": "Nombre maximum de client *",
            "en": ""
        },
        "clients": {
            "fr": "clients",
            "en": ""
        },
        "rdv": {
            "fr": "Lieu de rendez-vous",
            "en": ""
        },
        "contient": {
            "fr": "Contenu (objets, nourriture, ...)",
            "en": ""
        },
        "apporter": {
            "fr": "À apporter",
            "en": ""
        },
        "important": {
            "fr": "Informations importantes",
            "en": ""
        }
        ,
        "exigence": {
            "fr": "Exigences",
            "en": ""
        },
        "autre": {
            "fr": "Autre",
            "en": ""
        }
    }
}